{
  "$schema": "https://static.modelcontextprotocol.io/schemas/2025-12-11/server.schema.json",
  "name": "io.github.TheBaronofAI/okaneland-mcp",
  "description": "Verified AI-tool prices and AI product margin math for agents.",
  "repository": {
    "url": "https://github.com/TheBaronofAI/okaneland-mcp",
    "source": "github"
  },
  "websiteUrl": "https://okaneland.com/palette/keep/",
  "version": "0.1.1",
  "packages": [
    {
      "registryType": "npm",
      "identifier": "@okaneland/mcp",
      "version": "0.1.1",
      "transport": {
        "type": "stdio"
      }
    }
  ]
}
